amrnet/__init__.py
amrnet/data.py
amrnet/layers.py
amrnet/loss.py
amrnet/nn.py
amrnet/optimizers.py
amrnet/tensor.py
amrnet/train.py
amrnet-0.1.1.dist-info/LICENSE
amrnet-0.1.1.dist-info/METADATA
amrnet-0.1.1.dist-info/WHEEL
amrnet-0.1.1.dist-info/top_level.txt
amrnet-0.1.1.dist-info/RECORD
